<?xml version="1.0" encoding="UTF-8"?>

<ToolChain PatchFormat="1" ActiveSlot="1">
  <MetaParameterValues M1="0.5980941653251648"/>
  <Slot Type="Straightliner">
    <Slot1-Straightliner PatchFormat="1" MasterLevel="-15" GlideTime="103.499">
      <OscSection PatchFormat="1">
        <Osc1 PatchFormat="1" Level="-8.67" MidSide="0.36" StereoDetuneHz="0.23"
              StartPhase="125.58" CombHarmonic="1.49" CombAmount="67.4" SpectralSlope="-0.77"
              EvenOddRatio="0.515" PhaseShift="1" EvenOddPhaseShift="43" StereoPhaseShift="78"
              EvenOddStereoPhaseShift="97" AudioFileRelativePath="Samples/SingleCycle/Classic/Saw.flac"/>
        <Osc2 PatchFormat="1" Mute="1" Level="-6.02" LevelByKey="-11.74" Tune="-5.02"
              EvenOddRatio="0.925" PhaseShift="1" EvenOddPhaseShift="1" StereoPhaseShift="1"
              EvenOddStereoPhaseShift="1" AudioFileRelativePath="Samples/SingleCycle/Classic/Saw.flac"/>
        <Osc3 PatchFormat="1" Mute="1" Level="-4.24" StartPhase="98" PhaseShift="1"
              EvenOddPhaseShift="1" StereoPhaseShift="1" EvenOddStereoPhaseShift="1"
              AudioFileRelativePath="Samples/SingleCycle/Classic/Saw.flac"/>
        <Osc4 PatchFormat="1" Mute="1" PhaseShift="1" EvenOddPhaseShift="1"
              StereoPhaseShift="1" EvenOddStereoPhaseShift="1" AudioFileRelativePath="Samples/SingleCycle/Classic/Saw.flac"/>
      </OscSection>
      <Filter PatchFormat="1" Frequency="1000" Resonance="0" PreAllpass="20000"
              MakeUp="1" Order="1"/>
      <PitchEnvelope PatchFormat="1" TimeScale="1.0" GridX="1" GridY="1" ScaleFactor="1.0"
                     Offset="0.0" TimeScaleByKey="0.0" TimeScaleByVel="0.0" Depth="1.0"
                     DepthByKey="0.0" DepthByVel="0.0" SyncMode="1" LoopStartIndex="0"
                     LoopEndIndex="1" LoopMode="Off">
        <Breakpoint Time="0.0" Level="1.0" Shape="Analog" ShapeAmount="1.0"/>
        <Breakpoint Time="1.0" Level="1.0" Shape="Analog" ShapeAmount="1.0"/>
      </PitchEnvelope>
      <FilterEnvelope PatchFormat="1" TimeScale="1.0" GridX="1" GridY="1" ScaleFactor="1.0"
                      Offset="0.0" TimeScaleByKey="0.0" TimeScaleByVel="0.0" Depth="1.0"
                      DepthByKey="0.0" DepthByVel="0.0" SyncMode="1" LoopStartIndex="0"
                      LoopEndIndex="1" LoopMode="Forward">
        <Breakpoint Time="0.0" Level="1.0" Shape="Analog" ShapeAmount="1.0"/>
        <Breakpoint Time="1.0" Level="1.0" Shape="Analog" ShapeAmount="1.0"/>
        <Breakpoint Time="1.07654676" Level="1.0" Shape="Analog" ShapeAmount="1.0"/>
      </FilterEnvelope>
      <AmpEnvelope PatchFormat="1" TimeScale="1.0" GridX="1" GridY="1" ScaleFactor="1.0"
                   Offset="0.0" TimeScaleByKey="0.0" TimeScaleByVel="0.0" Depth="1.0"
                   DepthByKey="0.0" DepthByVel="0.0" SyncMode="1" LoopStartIndex="1"
                   LoopEndIndex="2" LoopMode="Forward">
        <Breakpoint Time="0.0" Level="0.0" Shape="Analog" ShapeAmount="1.0"/>
        <Breakpoint Time="0.01" Level="1.0" Shape="Analog" ShapeAmount="1.0"/>
        <Breakpoint Time="1.0" Level="1.0" Shape="Analog" ShapeAmount="1.0"/>
        <Breakpoint Time="1.2" Level="0.0" Shape="Analog" ShapeAmount="1.0"/>
      </AmpEnvelope>
    </Slot1-Straightliner>
  </Slot>
  <Slot Type="Quadrifex">
    <Slot2-Quadrifex PatchFormat="1" DryWet="0.7" Routing="1&gt;2&gt;3&gt;4" Slot1="WaveShaper"
                     Slot2="SlopeFilter" Slot3="Chorus" Slot4="Reverb">
      <RoutingMatrix5x5 PatchFormat="1"/>
      <WaveShaper1 PatchFormat="1" Drive="28.2" DC="0.17" OutputLevel="-10.9" Oversampling="2"/>
      <SlopeFilter2 PatchFormat="1" Slope="-3.14"/>
      <Chorus3 PatchFormat="1" Delay="24" Depth="1.17" StereoPhase="1" GlobalFeedback="1"
               CrossMix="1" FeedbackPostCrossMix="1" DryWetRatio="0.42" DelayScaleVoice1="75"
               DepthScaleVoice1="56" AmpScaleVoice1="44" DepthScaleVoice2="-24"
               AmpScaleVoice2="51" DepthScaleVoice3="-43" AmpScaleVoice3="-27"
               DepthScaleVoice4="32" AmpScaleVoice4="-19"/>
      <Reverb4 PatchFormat="1" DryWetRatio="0.29" FirstEcho="50" PreDelay="1"
               DecayTime="4.86" LowDecayScale="1" HighCrossoverFrequency="4000"
               LowCrossoverFrequency="250" Pinking="0"/>
    </Slot2-Quadrifex>
  </Slot>
  <Slot Type="StereoDelay">
    <Slot3-StereoDelay PatchFormat="1" DelayScaleR="1.5" DiffusorTimeR="13.96" DiffusorAmountL="-14.1"
                       DiffusorAmountR="16.3" LowpassCutoffL="7535.59" LowpassCutoffR="4802.47"
                       HighpassCutoffL="83.29" HighpassCutoffR="59.41" FeedbackLeftToLeft="64.1"
                       FeedbackRightToRight="52.2" FeedbackLeftToRight="-13" FeedbackRightToLeft="13"
                       DryWet="24.4186" DelayInBeatsL="0.5" DelayInBeatsR="0.5"/>
  </Slot>
  <Slot Type="None">
    <Slot4-None PatchFormat="1"/>
  </Slot>
</ToolChain>
